rtl files/instruction_decoder.v
`timescale 1ns / 1ps
//////////////////////////////////////////////////////////////////////////////////
// Company: 
// Engineer: 
// 
// Create Date:    20:01:48 08/26/2026 
// Design Name: 
// Module Name:    instruction_decoder 
// Project Name: 
// Target Devices: 
// Tool versions: 
// Description: 
//
// Dependencies: 
//
// Revision: 
// Revision 0.01 - File Created
// Additional Comments: 
//
//////////////////////////////////////////////////////////////////////////////////
`timescale 1ns/1ps

module instruction_decoder (

    input [31:0] instruction,

    // Register fields
    output [4:0] rs1,
    output [4:0] rs2,
    output [4:0] rd,

    // Immediate
    output reg [31:0] Immediate,

    // ALU control
    output reg [3:0] ALU_Opcode,

    // Shift amount
    output reg [4:0] Shamt,

    // Control signals
    output reg ALUSrc,
    output reg RegWrite
);

    //==================================================
    // RISC-V OPCODES
    //==================================================

    localparam OPCODE_RTYPE = 7'b0110011;
    localparam OPCODE_ITYPE = 7'b0010011;


    //==================================================
    // ALU OPCODES
    //==================================================

    localparam ALU_ADD  = 4'b0000;
    localparam ALU_SUB  = 4'b0001;
    localparam ALU_AND  = 4'b0010;
    localparam ALU_OR   = 4'b0011;
    localparam ALU_XOR  = 4'b0100;

    localparam ALU_SLL  = 4'b0110;
    localparam ALU_SRL  = 4'b0111;

    localparam ALU_SLT  = 4'b1000;
    localparam ALU_SLTU = 4'b1001;


    //==================================================
    // EXTRACT REGISTER FIELDS
    //==================================================

    assign rd  = instruction[11:7];
    assign rs1 = instruction[19:15];
    assign rs2 = instruction[24:20];


    //==================================================
    // INTERNAL INSTRUCTION FIELDS
    //==================================================

    wire [6:0] opcode;
    wire [6:0] funct7;
    wire [2:0] funct3;

    assign opcode = instruction[6:0];
    assign funct3 = instruction[14:12];
    assign funct7 = instruction[31:25];


    //==================================================
    // DECODER
    //==================================================

    always @(*) begin

        // Default values

        Immediate = 32'b0;

        ALU_Opcode = ALU_ADD;

        Shamt = 5'b0;

        ALUSrc = 1'b0;

        RegWrite = 1'b0;


        case (opcode)

            //================================================
            // R-TYPE
            //================================================

            OPCODE_RTYPE: begin

                RegWrite = 1'b1;
                ALUSrc = 1'b0;

                case (funct3)

                    // ADD / SUB
                    3'b000: begin

                        if (funct7 == 7'b0100000)
                            ALU_Opcode = ALU_SUB;
                        else
                            ALU_Opcode = ALU_ADD;

                    end


                    // SLL
                    3'b001: begin
							  ALU_Opcode = ALU_SLL;
							  Shamt = instruction[24:20];
						  end


                    // SLT
                    3'b010: begin
                        ALU_Opcode = ALU_SLT;
                    end


                    // SLTU
                    3'b011: begin
                        ALU_Opcode = ALU_SLTU;
                    end


                    // XOR
                    3'b100: begin
                        ALU_Opcode = ALU_XOR;
                    end


                    // SRL
                    3'b101: begin
								ALU_Opcode = ALU_SRL;
								Shamt = instruction[24:20];
						  end


                    // OR
                    3'b110: begin
                        ALU_Opcode = ALU_OR;
                    end


                    // AND
                    3'b111: begin
                        ALU_Opcode = ALU_AND;
                    end


                    default: begin
                        ALU_Opcode = ALU_ADD;
                        RegWrite = 1'b0;
                    end

                endcase

            end


            //================================================
            // I-TYPE
            //================================================

            OPCODE_ITYPE: begin

                RegWrite = 1'b1;
                ALUSrc = 1'b1;

                // Sign extend 12-bit immediate

                Immediate = {{20{instruction[31]}},
                             instruction[31:20]};


                case (funct3)

                    // ADDI
                    3'b000: begin
                        ALU_Opcode = ALU_ADD;
                    end


                    // SLLI
                    3'b001: begin

                        ALU_Opcode = ALU_SLL;

                        Shamt = instruction[24:20];

                    end


                    // SLTI
                    3'b010: begin
                        ALU_Opcode = ALU_SLT;
                    end


                    // SLTIU
                    3'b011: begin
                        ALU_Opcode = ALU_SLTU;
                    end


                    // XORI
                    3'b100: begin
                        ALU_Opcode = ALU_XOR;
                    end


                    // SRLI
                    3'b101: begin

                        ALU_Opcode = ALU_SRL;

                        Shamt = instruction[24:20];

                    end


                    // ORI
                    3'b110: begin
                        ALU_Opcode = ALU_OR;
                    end


                    // ANDI
                    3'b111: begin
                        ALU_Opcode = ALU_AND;
                    end


                    default: begin
                        ALU_Opcode = ALU_ADD;
                        RegWrite = 1'b0;
                    end

                endcase

            end


            //================================================
            // UNSUPPORTED INSTRUCTION
            //================================================

            default: begin

                Immediate = 32'b0;

                ALU_Opcode = ALU_ADD;

                Shamt = 5'b0;

                ALUSrc = 1'b0;

                RegWrite = 1'b0;

            end

        endcase

    end

endmodule

tb files/tb_instruction_decoder.v
`timescale 1ns / 1ps

////////////////////////////////////////////////////////////////////////////////
// Company: 
// Engineer:
//
// Create Date:   20:05:57 08/26/2026
// Design Name:   instruction_decoder
// Module Name:   C:/Users/Hendrick/Desktop/Xilinx projects/alu_32bit/tb_instruction_decoder.v
// Project Name:  alu_32bit
// Target Device:  
// Tool versions:  
// Description: 
//
// Verilog Test Fixture created by ISE for module: instruction_decoder
//
// Dependencies:
// 
// Revision:
// Revision 0.01 - File Created
// Additional Comments:
// 
////////////////////////////////////////////////////////////////////////////////

`timescale 1ns/1ps

module tb_instruction_decoder;

    reg [31:0] instruction;

    wire [4:0] rs1;
    wire [4:0] rs2;
    wire [4:0] rd;

    wire [31:0] Immediate;

    wire [3:0] ALU_Opcode;

    wire [4:0] Shamt;

    wire ALUSrc;
    wire RegWrite;


    //==================================================
    // DUT
    //==================================================

    instruction_decoder uut (

        .instruction(instruction),

        .rs1(rs1),
        .rs2(rs2),
        .rd(rd),

        .Immediate(Immediate),

        .ALU_Opcode(ALU_Opcode),

        .Shamt(Shamt),

        .ALUSrc(ALUSrc),
        .RegWrite(RegWrite)

    );


    //==================================================
    // VCD
    //==================================================

    initial begin

        $dumpfile("instruction_decoder.vcd");

        $dumpvars(0, tb_instruction_decoder);

    end


    //==================================================
    // TEST
    //==================================================

    initial begin

        //================================================
        // ADD x3,x1,x2
        //================================================

        instruction = 32'h002081B3;

        #10;

        $display("ADD  : instr=%h rs1=%d rs2=%d rd=%d ALU=%b SRC=%b WE=%b",
                 instruction, rs1, rs2, rd,
                 ALU_Opcode, ALUSrc, RegWrite);


        //================================================
        // SUB x3,x1,x2
        //================================================

        instruction = 32'h402081B3;

        #10;

        $display("SUB  : instr=%h rs1=%d rs2=%d rd=%d ALU=%b SRC=%b WE=%b",
                 instruction, rs1, rs2, rd,
                 ALU_Opcode, ALUSrc, RegWrite);


        //================================================
        // AND x3,x1,x2
        //================================================

        instruction = 32'h0020F1B3;

        #10;

        $display("AND  : instr=%h rs1=%d rs2=%d rd=%d ALU=%b SRC=%b WE=%b",
                 instruction, rs1, rs2, rd,
                 ALU_Opcode, ALUSrc, RegWrite);


        //================================================
        // OR x3,x1,x2
        //================================================

        instruction = 32'h0020E1B3;

        #10;

        $display("OR   : instr=%h rs1=%d rs2=%d rd=%d ALU=%b SRC=%b WE=%b",
                 instruction, rs1, rs2, rd,
                 ALU_Opcode, ALUSrc, RegWrite);


        //================================================
        // XOR x3,x1,x2
        //================================================

        instruction = 32'h0020C1B3;

        #10;

        $display("XOR  : instr=%h rs1=%d rs2=%d rd=%d ALU=%b SRC=%b WE=%b",
                 instruction, rs1, rs2, rd,
                 ALU_Opcode, ALUSrc, RegWrite);


        //================================================
        // SLT x3,x1,x2
        //================================================

        instruction = 32'h0020A1B3;

        #10;

        $display("SLT  : instr=%h rs1=%d rs2=%d rd=%d ALU=%b SRC=%b WE=%b",
                 instruction, rs1, rs2, rd,
                 ALU_Opcode, ALUSrc, RegWrite);


        //================================================
        // SLTU x3,x1,x2
        //================================================

        instruction = 32'h0020B1B3;

        #10;

        $display("SLTU : instr=%h rs1=%d rs2=%d rd=%d ALU=%b SRC=%b WE=%b",
                 instruction, rs1, rs2, rd,
                 ALU_Opcode, ALUSrc, RegWrite);


        //================================================
        // SLL x3,x1,x2
        //================================================

        instruction = 32'h002091B3;

        #10;

        $display("SLL  : instr=%h rs1=%d rs2=%d rd=%d ALU=%b SRC=%b WE=%b",
                 instruction, rs1, rs2, rd,
                 ALU_Opcode, ALUSrc, RegWrite);


        //================================================
        // SRL x3,x1,x2
        //================================================

        instruction = 32'h0020D1B3;

        #10;

        $display("SRL  : instr=%h rs1=%d rs2=%d rd=%d ALU=%b SRC=%b WE=%b",
                 instruction, rs1, rs2, rd,
                 ALU_Opcode, ALUSrc, RegWrite);


        //================================================
        // ADDI x1,x0,10
        //================================================

        instruction = 32'h00A00093;

        #10;

        $display("ADDI : instr=%h rs1=%d rd=%d IMM=%h ALU=%b SRC=%b WE=%b",
                 instruction, rs1, rd,
                 Immediate,
                 ALU_Opcode, ALUSrc, RegWrite);


        //================================================
        // ADDI x2,x0,20
        //================================================

        instruction = 32'h01400113;

        #10;

        $display("ADDI : instr=%h rs1=%d rd=%d IMM=%h ALU=%b SRC=%b WE=%b",
                 instruction, rs1, rd,
                 Immediate,
                 ALU_Opcode, ALUSrc, RegWrite);


        //================================================
        // ANDI x3,x1,15
        //================================================

        instruction = 32'h00F0F193;

        #10;

        $display("ANDI : instr=%h rs1=%d rd=%d IMM=%h ALU=%b SRC=%b WE=%b",
                 instruction, rs1, rd,
                 Immediate,
                 ALU_Opcode, ALUSrc, RegWrite);


        //================================================
        // ORI x3,x1,15
        //================================================

        instruction = 32'h00F0E193;

        #10;

        $display("ORI  : instr=%h rs1=%d rd=%d IMM=%h ALU=%b SRC=%b WE=%b",
                 instruction, rs1, rd,
                 Immediate,
                 ALU_Opcode, ALUSrc, RegWrite);


        //================================================
        // XORI x3,x1,15
        //================================================

        instruction = 32'h00F0C193;

        #10;

        $display("XORI : instr=%h rs1=%d rd=%d IMM=%h ALU=%b SRC=%b WE=%b",
                 instruction, rs1, rd,
                 Immediate,
                 ALU_Opcode, ALUSrc, RegWrite);


        //================================================
        // SLLI x3,x1,4
        //================================================

        instruction = 32'h00409193;

        #10;

        $display("SLLI : instr=%h rs1=%d rd=%d SHAMT=%d ALU=%b SRC=%b WE=%b",
                 instruction, rs1, rd,
                 Shamt,
                 ALU_Opcode, ALUSrc, RegWrite);


        //================================================
        // SRLI x3,x1,4
        //================================================

        instruction = 32'h0040D193;

        #10;

        $display("SRLI : instr=%h rs1=%d rd=%d SHAMT=%d ALU=%b SRC=%b WE=%b",
                 instruction, rs1, rd,
                 Shamt,
                 ALU_Opcode, ALUSrc, RegWrite);


        //================================================
        // FINISH
        //================================================

        #10;

        $finish;

    end

endmodule

power vcd files/instruction_decoder.vcd
$date
   Wed Aug 26 20:14:41 2026
$end
$version
  P.20131013
$end
$timescale
  1ps
$end
$scope module tb_instruction_decoder $end
$var wire 1 | rs1 [4] $end
$var wire 1 } rs1 [3] $end
$var wire 1 ~ rs1 [2] $end
$var wire 1 !! rs1 [1] $end
$var wire 1 "! rs1 [0] $end
$var wire 1 #! rs2 [4] $end
$var wire 1 $! rs2 [3] $end
$var wire 1 %! rs2 [2] $end
$var wire 1 &! rs2 [1] $end
$var wire 1 '! rs2 [0] $end
$var wire 1 (! rd [4] $end
$var wire 1 )! rd [3] $end
$var wire 1 *! rd [2] $end
$var wire 1 +! rd [1] $end
$var wire 1 ,! rd [0] $end
$var wire 1 0 Immediate [31] $end
$var wire 1 1 Immediate [30] $end
$var wire 1 2 Immediate [29] $end
$var wire 1 3 Immediate [28] $end
$var wire 1 4 Immediate [27] $end
$var wire 1 5 Immediate [26] $end
$var wire 1 6 Immediate [25] $end
$var wire 1 7 Immediate [24] $end
$var wire 1 8 Immediate [23] $end
$var wire 1 9 Immediate [22] $end
$var wire 1 : Immediate [21] $end
$var wire 1 ; Immediate [20] $end
$var wire 1 < Immediate [19] $end
$var wire 1 = Immediate [18] $end
$var wire 1 > Immediate [17] $end
$var wire 1 ? Immediate [16] $end
$var wire 1 @ Immediate [15] $end
$var wire 1 A Immediate [14] $end
$var wire 1 B Immediate [13] $end
$var wire 1 C Immediate [12] $end
$var wire 1 D Immediate [11] $end
$var wire 1 E Immediate [10] $end
$var wire 1 F Immediate [9] $end
$var wire 1 G Immediate [8] $end
$var wire 1 H Immediate [7] $end
$var wire 1 I Immediate [6] $end
$var wire 1 J Immediate [5] $end
$var wire 1 K Immediate [4] $end
$var wire 1 L Immediate [3] $end
$var wire 1 M Immediate [2] $end
$var wire 1 N Immediate [1] $end
$var wire 1 O Immediate [0] $end
$var wire 1 P ALU_Opcode [3] $end
$var wire 1 Q ALU_Opcode [2] $end
$var wire 1 R ALU_Opcode [1] $end
$var wire 1 S ALU_Opcode [0] $end
$var wire 1 T Shamt [4] $end
$var wire 1 U Shamt [3] $end
$var wire 1 V Shamt [2] $end
$var wire 1 W Shamt [1] $end
$var wire 1 X Shamt [0] $end
$var wire 1 Y ALUSrc $end
$var wire 1 Z RegWrite $end
$var reg 32 [ instruction [31:0] $end
$scope module uut $end
$var wire 1 \ instruction [31] $end
$var wire 1 ] instruction [30] $end
$var wire 1 ^ instruction [29] $end
$var wire 1 _ instruction [28] $end
$var wire 1 ` instruction [27] $end
$var wire 1 a instruction [26] $end
$var wire 1 b instruction [25] $end
$var wire 1 c instruction [24] $end
$var wire 1 d instruction [23] $end
$var wire 1 e instruction [22] $end
$var wire 1 f instruction [21] $end
$var wire 1 g instruction [20] $end
$var wire 1 h instruction [19] $end
$var wire 1 i instruction [18] $end
$var wire 1 j instruction [17] $end
$var wire 1 k instruction [16] $end
$var wire 1 l instruction [15] $end
$var wire 1 m instruction [14] $end
$var wire 1 n instruction [13] $end
$var wire 1 o instruction [12] $end
$var wire 1 p instruction [11] $end
$var wire 1 q instruction [10] $end
$var wire 1 r instruction [9] $end
$var wire 1 s instruction [8] $end
$var wire 1 t instruction [7] $end
$var wire 1 u instruction [6] $end
$var wire 1 v instruction [5] $end
$var wire 1 w instruction [4] $end
$var wire 1 x instruction [3] $end
$var wire 1 y instruction [2] $end
$var wire 1 z instruction [1] $end
$var wire 1 { instruction [0] $end
$var wire 1 | rs1 [4] $end
$var wire 1 } rs1 [3] $end
$var wire 1 ~ rs1 [2] $end
$var wire 1 !! rs1 [1] $end
$var wire 1 "! rs1 [0] $end
$var wire 1 #! rs2 [4] $end
$var wire 1 $! rs2 [3] $end
$var wire 1 %! rs2 [2] $end
$var wire 1 &! rs2 [1] $end
$var wire 1 '! rs2 [0] $end
$var wire 1 (! rd [4] $end
$var wire 1 )! rd [3] $end
$var wire 1 *! rd [2] $end
$var wire 1 +! rd [1] $end
$var wire 1 ,! rd [0] $end
$var wire 1 -! opcode [6] $end
$var wire 1 .! opcode [5] $end
$var wire 1 /! opcode [4] $end
$var wire 1 0! opcode [3] $end
$var wire 1 1! opcode [2] $end
$var wire 1 2! opcode [1] $end
$var wire 1 3! opcode [0] $end
$var wire 1 4! funct7 [6] $end
$var wire 1 5! funct7 [5] $end
$var wire 1 6! funct7 [4] $end
$var wire 1 7! funct7 [3] $end
$var wire 1 8! funct7 [2] $end
$var wire 1 9! funct7 [1] $end
$var wire 1 :! funct7 [0] $end
$var wire 1 ;! funct3 [2] $end
$var wire 1 <! funct3 [1] $end
$var wire 1 =! funct3 [0] $end
$var reg 32 >! Immediate [31:0] $end
$var reg 4 ?! ALU_Opcode [3:0] $end
$var reg 5 @! Shamt [4:0] $end
$var reg 1 A! ALUSrc $end
$var reg 1 B! RegWrite $end
$upscope $end
$upscope $end
$enddefinitions $end
#0
$dumpvars
0V
1.!
09!
07!
06!
1Z
0U
0Q
00!
0Y
02
01!
0-!
13!
0:!
0X
0W
08!
0;
01
0S
04
08
06
03
0R
07
0P
0T
12!
05
00
0:
1/!
0<
09
b0 >!
b0 ?!
b0 @!
0A!
1B!
1"!
0!!
0~
0}
0|
0'!
1&!
0%!
0$!
0#!
b1000001000000110110011 [
1,!
1+!
0*!
0)!
0(!
0O
0N
0>
0K
0F
0E
0J
0M
0@
0D
0B
0I
0=
0H
0?
0C
0L
0G
0A
0q
0p
0o
0n
0m
1z
0u
1l
1w
0k
0j
04!
0<!
0;!
0=!
0x
1v
1t
0y
1s
05!
1{
0r
0`
0\
0e
0g
0d
0h
0c
0a
0b
0_
0]
1f
0^
0i
$end
#10000
1S
b1 ?!
1B!
b1000000001000001000000110110011 [
15!
1]
#20000
0S
1R
b10 ?!
1B!
b1000001111000110110011 [
1o
1n
1m
1<!
1;!
1=!
05!
0]
#30000
1S
b11 ?!
1B!
b1000001110000110110011 [
0o
0=!
#40000
1Q
0S
0R
b100 ?!
1B!
b1000001100000110110011 [
0n
0<!
#50000
0Q
1P
b1000 ?!
1B!
b1000001010000110110011 [
1n
0m
1<!
0;!
#60000
1S
b1001 ?!
1B!
b1000001011000110110011 [
1o
1=!
#70000
1Q
0S
1R
0P
b110 ?!
1B!
b1000001001000110110011 [
0n
0<!
#80000
1S
b111 ?!
1B!
b1000001101000110110011 [
1m
1;!
#90000
0.!
0U
0Q
1Y
0W
0S
0R
b1010 >!
b0 ?!
b0 @!
1A!
1B!
0"!
1$!
b101000000000000010010011 [
0+!
1N
1L
0o
0m
0l
0;!
0=!
0v
0s
1d
#100000
b10100 >!
1A!
1B!
0&!
1%!
0$!
1#!
b1010000000000000100010011 [
0,!
1+!
0N
1K
1M
0L
0t
1s
1e
0d
1c
0f
#110000
1R
b1111 >!
b10 ?!
1A!
1B!
1"!
1'!
1&!
1$!
0#!
b111100001111000110010011 [
1,!
1O
1N
0K
1L
1o
1n
1m
1l
1<!
1;!
1=!
1t
1g
1d
0c
1f
#120000
1S
b1111 >!
b11 ?!
1A!
1B!
b111100001110000110010011 [
0o
0=!
#130000
1Q
0S
0R
b1111 >!
b100 ?!
1A!
1B!
b111100001100000110010011 [
0n
0<!
#140000
1V
1R
b100 >!
b110 ?!
b100 @!
1A!
1B!
0'!
0&!
0$!
b10000001001000110010011 [
0O
0N
0L
1o
0m
0;!
1=!
0g
0d
0f
#150000
1S
b100 >!
b111 ?!
b100 @!
1A!
1B!
b10000001101000110010011 [
1m
1;!
