rtl files/reg_file.v
`timescale 1ns / 1ps
//////////////////////////////////////////////////////////////////////////////////
// Company: 
// Engineer: 
// 
// Create Date:    19:12:42 08/26/2026 
// Design Name: 
// Module Name:    reg_file 
// Project Name: 
// Target Devices: 
// Tool versions: 
// Description: 
//
// Dependencies: 
//
// Revision: 
// Revision 0.01 - File Created
// Additional Comments: 
//
//////////////////////////////////////////////////////////////////////////////////
`timescale 1ns/1ps

module reg_file #(
    parameter WIDTH = 32,
    parameter DEPTH = 32
)(
    input clk,
    input reset,

    //==================================================
    // READ PORT 1
    //==================================================

    input [4:0] ReadAddr1,
    output [WIDTH-1:0] ReadData1,

    //==================================================
    // READ PORT 2
    //==================================================

    input [4:0] ReadAddr2,
    output [WIDTH-1:0] ReadData2,

    //==================================================
    // WRITE PORT
    //==================================================

    input [4:0] WriteAddr,
    input [WIDTH-1:0] WriteData,
    input WriteEnable
);


    //==================================================
    // REGISTER ARRAY
    //==================================================

    reg [WIDTH-1:0] registers [0:DEPTH-1];

    integer i;


    //==================================================
    // SYNCHRONOUS WRITE
    //==================================================

    always @(posedge clk) begin

        if (reset) begin

            for (i = 0; i < DEPTH; i = i + 1)
                registers[i] <= {WIDTH{1'b0}};

        end

        else begin

            // x0 is always zero
            registers[0] <= {WIDTH{1'b0}};

            // Write only if enabled
            // and destination is not x0
            if (WriteEnable && (WriteAddr != 5'd0))
                registers[WriteAddr] <= WriteData;

        end

    end


    //==================================================
    // ASYNCHRONOUS READ PORT 1
    //==================================================

    assign ReadData1 =
        (ReadAddr1 == 5'd0) ?
        {WIDTH{1'b0}} :
        registers[ReadAddr1];


    //==================================================
    // ASYNCHRONOUS READ PORT 2
    //==================================================

    assign ReadData2 =
        (ReadAddr2 == 5'd0) ?
        {WIDTH{1'b0}} :
        registers[ReadAddr2];


endmodule

tb files/tb_reg.v
`timescale 1ns / 1ps

////////////////////////////////////////////////////////////////////////////////
// Company: 
// Engineer:
//
// Create Date:   19:13:44 08/26/2026
// Design Name:   reg_file
// Module Name:   C:/Users/Hendrick/Desktop/Xilinx projects/alu_32bit/tb_reg.v
// Project Name:  alu_32bit
// Target Device:  
// Tool versions:  
// Description: 
//
// Verilog Test Fixture created by ISE for module: reg_file
//
// Dependencies:
// 
// Revision:
// Revision 0.01 - File Created
// Additional Comments:
// 
////////////////////////////////////////////////////////////////////////////////

`timescale 1ns/1ps

module tb_reg;

    //==================================================
    // Clock and Reset
    //==================================================

    reg clk;
    reg reset;


    //==================================================
    // READ PORTS
    //==================================================

    reg [4:0] ReadAddr1;
    reg [4:0] ReadAddr2;

    wire [31:0] ReadData1;
    wire [31:0] ReadData2;


    //==================================================
    // WRITE PORT
    //==================================================

    reg [4:0] WriteAddr;
    reg [31:0] WriteData;
    reg WriteEnable;


    //==================================================
    // DUT
    //==================================================

    reg_file #(
        .WIDTH(32),
        .DEPTH(32)
    ) uut (

        .clk(clk),
        .reset(reset),

        .ReadAddr1(ReadAddr1),
        .ReadData1(ReadData1),

        .ReadAddr2(ReadAddr2),
        .ReadData2(ReadData2),

        .WriteAddr(WriteAddr),
        .WriteData(WriteData),
        .WriteEnable(WriteEnable)

    );


    //==================================================
    // CLOCK GENERATION
    //==================================================

    initial begin

        clk = 1'b0;

        forever #5 clk = ~clk;

    end


    //==================================================
    // VCD
    //==================================================

    initial begin

        $dumpfile("register_file.vcd");

        $dumpvars(0, tb_reg);

    end


    //==================================================
    // MONITOR
    //==================================================

    initial begin

        $display("--------------------------------------------------------------------------");

        $display("TIME  WE  WA   WD          RA1   RD1         RA2   RD2");

        $display("--------------------------------------------------------------------------");

        $monitor("%4dns  %b   %02d   %h   %02d    %h   %02d    %h",
                 $time,
                 WriteEnable,
                 WriteAddr,
                 WriteData,
                 ReadAddr1,
                 ReadData1,
                 ReadAddr2,
                 ReadData2);

    end


    //==================================================
    // TEST SEQUENCE
    //==================================================

    initial begin


        //================================================
        // INITIAL VALUES
        //================================================

        reset = 1'b1;

        WriteEnable = 1'b0;

        WriteAddr = 5'd0;

        WriteData = 32'h00000000;

        ReadAddr1 = 5'd0;

        ReadAddr2 = 5'd0;


        // Hold reset
        #20;


        // Release reset
        reset = 1'b0;


        //================================================
        // WRITE x1 = 100
        //================================================

        WriteEnable = 1'b1;

        WriteAddr = 5'd1;

        WriteData = 32'h00000064;

        #10;


        //================================================
        // WRITE x2 = 200
        //================================================

        WriteAddr = 5'd2;

        WriteData = 32'h000000C8;

        #10;


        //================================================
        // STOP WRITING
        //================================================

        WriteEnable = 1'b0;


        //================================================
        // READ x1 AND x2
        //================================================

        ReadAddr1 = 5'd1;

        ReadAddr2 = 5'd2;

        #10;


        $display("READ TEST:");
        $display("x1 = %h", ReadData1);
        $display("x2 = %h", ReadData2);


        //================================================
        // WRITE x10
        //================================================

        WriteEnable = 1'b1;

        WriteAddr = 5'd10;

        WriteData = 32'h12345678;

        #10;


        // Stop writing
        WriteEnable = 1'b0;


        //================================================
        // READ x10 AND x1
        //================================================

        ReadAddr1 = 5'd10;

        ReadAddr2 = 5'd1;

        #10;


        $display("x10 = %h", ReadData1);
        $display("x1  = %h", ReadData2);


        //================================================
        // TEST x0
        //================================================

        // Try to write FFFFFFFF to x0

        WriteEnable = 1'b1;

        WriteAddr = 5'd0;

        WriteData = 32'hFFFFFFFF;

        #10;


        // Stop writing
        WriteEnable = 1'b0;


        // Read x0
        ReadAddr1 = 5'd0;

        ReadAddr2 = 5'd0;

        #10;


        $display("x0 = %h", ReadData1);


        //================================================
        // FINISH
        //================================================

        $finish;

    end

endmodule

power vcd files/register_file.vcd
$date
   Wed Aug 26 20:15:02 2026
$end
$version
  P.20131013
$end
$timescale
  1ps
$end
$scope module tb_reg $end
$var wire 1 o ReadData1 [31] $end
$var wire 1 p ReadData1 [30] $end
$var wire 1 q ReadData1 [29] $end
$var wire 1 r ReadData1 [28] $end
$var wire 1 s ReadData1 [27] $end
$var wire 1 t ReadData1 [26] $end
$var wire 1 u ReadData1 [25] $end
$var wire 1 v ReadData1 [24] $end
$var wire 1 w ReadData1 [23] $end
$var wire 1 x ReadData1 [22] $end
$var wire 1 y ReadData1 [21] $end
$var wire 1 z ReadData1 [20] $end
$var wire 1 { ReadData1 [19] $end
$var wire 1 | ReadData1 [18] $end
$var wire 1 } ReadData1 [17] $end
$var wire 1 ~ ReadData1 [16] $end
$var wire 1 !! ReadData1 [15] $end
$var wire 1 "! ReadData1 [14] $end
$var wire 1 #! ReadData1 [13] $end
$var wire 1 $! ReadData1 [12] $end
$var wire 1 %! ReadData1 [11] $end
$var wire 1 &! ReadData1 [10] $end
$var wire 1 '! ReadData1 [9] $end
$var wire 1 (! ReadData1 [8] $end
$var wire 1 )! ReadData1 [7] $end
$var wire 1 *! ReadData1 [6] $end
$var wire 1 +! ReadData1 [5] $end
$var wire 1 ,! ReadData1 [4] $end
$var wire 1 -! ReadData1 [3] $end
$var wire 1 .! ReadData1 [2] $end
$var wire 1 /! ReadData1 [1] $end
$var wire 1 0! ReadData1 [0] $end
$var wire 1 6! ReadData2 [31] $end
$var wire 1 7! ReadData2 [30] $end
$var wire 1 8! ReadData2 [29] $end
$var wire 1 9! ReadData2 [28] $end
$var wire 1 :! ReadData2 [27] $end
$var wire 1 ;! ReadData2 [26] $end
$var wire 1 <! ReadData2 [25] $end
$var wire 1 =! ReadData2 [24] $end
$var wire 1 >! ReadData2 [23] $end
$var wire 1 ?! ReadData2 [22] $end
$var wire 1 @! ReadData2 [21] $end
$var wire 1 A! ReadData2 [20] $end
$var wire 1 B! ReadData2 [19] $end
$var wire 1 C! ReadData2 [18] $end
$var wire 1 D! ReadData2 [17] $end
$var wire 1 E! ReadData2 [16] $end
$var wire 1 F! ReadData2 [15] $end
$var wire 1 G! ReadData2 [14] $end
$var wire 1 H! ReadData2 [13] $end
$var wire 1 I! ReadData2 [12] $end
$var wire 1 J! ReadData2 [11] $end
$var wire 1 K! ReadData2 [10] $end
$var wire 1 L! ReadData2 [9] $end
$var wire 1 M! ReadData2 [8] $end
$var wire 1 N! ReadData2 [7] $end
$var wire 1 O! ReadData2 [6] $end
$var wire 1 P! ReadData2 [5] $end
$var wire 1 Q! ReadData2 [4] $end
$var wire 1 R! ReadData2 [3] $end
$var wire 1 S! ReadData2 [2] $end
$var wire 1 T! ReadData2 [1] $end
$var wire 1 U! ReadData2 [0] $end
$var reg 1 a clk $end
$var reg 1 b reset $end
$var reg 5 c ReadAddr1 [4:0] $end
$var reg 5 d ReadAddr2 [4:0] $end
$var reg 5 e WriteAddr [4:0] $end
$var reg 32 f WriteData [31:0] $end
$var reg 1 g WriteEnable $end
$scope module uut $end
$var wire 1 h clk $end
$var wire 1 i reset $end
$var wire 1 j ReadAddr1 [4] $end
$var wire 1 k ReadAddr1 [3] $end
$var wire 1 l ReadAddr1 [2] $end
$var wire 1 m ReadAddr1 [1] $end
$var wire 1 n ReadAddr1 [0] $end
$var wire 1 o ReadData1 [31] $end
$var wire 1 p ReadData1 [30] $end
$var wire 1 q ReadData1 [29] $end
$var wire 1 r ReadData1 [28] $end
$var wire 1 s ReadData1 [27] $end
$var wire 1 t ReadData1 [26] $end
$var wire 1 u ReadData1 [25] $end
$var wire 1 v ReadData1 [24] $end
$var wire 1 w ReadData1 [23] $end
$var wire 1 x ReadData1 [22] $end
$var wire 1 y ReadData1 [21] $end
$var wire 1 z ReadData1 [20] $end
$var wire 1 { ReadData1 [19] $end
$var wire 1 | ReadData1 [18] $end
$var wire 1 } ReadData1 [17] $end
$var wire 1 ~ ReadData1 [16] $end
$var wire 1 !! ReadData1 [15] $end
$var wire 1 "! ReadData1 [14] $end
$var wire 1 #! ReadData1 [13] $end
$var wire 1 $! ReadData1 [12] $end
$var wire 1 %! ReadData1 [11] $end
$var wire 1 &! ReadData1 [10] $end
$var wire 1 '! ReadData1 [9] $end
$var wire 1 (! ReadData1 [8] $end
$var wire 1 )! ReadData1 [7] $end
$var wire 1 *! ReadData1 [6] $end
$var wire 1 +! ReadData1 [5] $end
$var wire 1 ,! ReadData1 [4] $end
$var wire 1 -! ReadData1 [3] $end
$var wire 1 .! ReadData1 [2] $end
$var wire 1 /! ReadData1 [1] $end
$var wire 1 0! ReadData1 [0] $end
$var wire 1 1! ReadAddr2 [4] $end
$var wire 1 2! ReadAddr2 [3] $end
$var wire 1 3! ReadAddr2 [2] $end
$var wire 1 4! ReadAddr2 [1] $end
$var wire 1 5! ReadAddr2 [0] $end
$var wire 1 6! ReadData2 [31] $end
$var wire 1 7! ReadData2 [30] $end
$var wire 1 8! ReadData2 [29] $end
$var wire 1 9! ReadData2 [28] $end
$var wire 1 :! ReadData2 [27] $end
$var wire 1 ;! ReadData2 [26] $end
$var wire 1 <! ReadData2 [25] $end
$var wire 1 =! ReadData2 [24] $end
$var wire 1 >! ReadData2 [23] $end
$var wire 1 ?! ReadData2 [22] $end
$var wire 1 @! ReadData2 [21] $end
$var wire 1 A! ReadData2 [20] $end
$var wire 1 B! ReadData2 [19] $end
$var wire 1 C! ReadData2 [18] $end
$var wire 1 D! ReadData2 [17] $end
$var wire 1 E! ReadData2 [16] $end
$var wire 1 F! ReadData2 [15] $end
$var wire 1 G! ReadData2 [14] $end
$var wire 1 H! ReadData2 [13] $end
$var wire 1 I! ReadData2 [12] $end
$var wire 1 J! ReadData2 [11] $end
$var wire 1 K! ReadData2 [10] $end
$var wire 1 L! ReadData2 [9] $end
$var wire 1 M! ReadData2 [8] $end
$var wire 1 N! ReadData2 [7] $end
$var wire 1 O! ReadData2 [6] $end
$var wire 1 P! ReadData2 [5] $end
$var wire 1 Q! ReadData2 [4] $end
$var wire 1 R! ReadData2 [3] $end
$var wire 1 S! ReadData2 [2] $end
$var wire 1 T! ReadData2 [1] $end
$var wire 1 U! ReadData2 [0] $end
$var wire 1 V! WriteAddr [4] $end
$var wire 1 W! WriteAddr [3] $end
$var wire 1 X! WriteAddr [2] $end
$var wire 1 Y! WriteAddr [1] $end
$var wire 1 Z! WriteAddr [0] $end
$var wire 1 [! WriteData [31] $end
$var wire 1 \! WriteData [30] $end
$var wire 1 ]! WriteData [29] $end
$var wire 1 ^! WriteData [28] $end
$var wire 1 _! WriteData [27] $end
$var wire 1 `! WriteData [26] $end
$var wire 1 a! WriteData [25] $end
$var wire 1 b! WriteData [24] $end
$var wire 1 c! WriteData [23] $end
$var wire 1 d! WriteData [22] $end
$var wire 1 e! WriteData [21] $end
$var wire 1 f! WriteData [20] $end
$var wire 1 g! WriteData [19] $end
$var wire 1 h! WriteData [18] $end
$var wire 1 i! WriteData [17] $end
$var wire 1 j! WriteData [16] $end
$var wire 1 k! WriteData [15] $end
$var wire 1 l! WriteData [14] $end
$var wire 1 m! WriteData [13] $end
$var wire 1 n! WriteData [12] $end
$var wire 1 o! WriteData [11] $end
$var wire 1 p! WriteData [10] $end
$var wire 1 q! WriteData [9] $end
$var wire 1 r! WriteData [8] $end
$var wire 1 s! WriteData [7] $end
$var wire 1 t! WriteData [6] $end
$var wire 1 u! WriteData [5] $end
$var wire 1 v! WriteData [4] $end
$var wire 1 w! WriteData [3] $end
$var wire 1 x! WriteData [2] $end
$var wire 1 y! WriteData [1] $end
$var wire 1 z! WriteData [0] $end
$var wire 1 {! WriteEnable $end
$var reg 1024 |! registers [31:0] $end
$var integer 32 }! i $end
$upscope $end
$upscope $end
$enddefinitions $end
#0
$dumpvars
0;!
0@!
0E!
0K!
0C!
0B!
0L!
09!
07!
0P!
0<!
0Q!
06!
0R!
0I!
0O!
0N!
0M!
0J!
0G!
0F!
0S!
0A!
0>!
0H!
0D!
0?!
0=!
0:!
08!
bx |!
bx }!
0+!
0*!
0)!
0(!
00!
0/!
0.!
0-!
0,!
0a
1b
b0 c
b0 d
b0 e
b0 f
0g
0'!
0&!
0%!
0$!
0#!
0"!
0!!
0~
0z
0y
0r
0q
0o
0v
0x
0U!
0T!
0w
0p
0}
0t
0s
0u
0|
0{
0w!
02!
0n
0y!
0t!
0s!
0o!
0h
0Y!
0V!
0v!
0r!
0Z!
0X!
0l
0W!
0j
0k
0z!
05!
04!
01!
0x!
0u!
1i
0m
0q!
0p!
03!
0^!
0n!
0l!
0f!
0c!
0d!
0_!
0`!
0e!
0h!
0]!
0{!
0m!
0b!
0i!
0\!
0a!
0k!
0g!
0[!
0j!
$end
#5000
b0 |!
b100000 }!
1a
1h
#10000
0a
0h
#15000
b100000 }!
1a
1h
#20000
0a
0b
b1 e
b1100100 f
1g
1t!
0h
1Z!
1x!
1u!
0i
1{!
#25000
b1100100000000000000000000000000000000000000000000000000000000000000000000000000000000000000000000000000000000000000000000000000000000000000000000000000000000000000000000000000000000000000000000000000000000000000000000000000000000000000000000000000000000000000000000000000000000000000000000000000000000000000000000000000000000000000000000000000000000000000000000000000000000000000000000000000000000000000000000000000000000000000000000000000000000000000000000000000000000000000000000000000000000000000000000000000000000000000000000000000000000000000000000000000000000000000000000000000000000000000000000000000000000000000000000000000000000000000000000000000000000000000000000000000000000000000000000000000000000000000000000000000000000000000000000000000000000000000000000000000000000000000000000000000000000000000000000000000000000000000000000000000000000000000000000000000000000000000000000000000000000000000000000000000000000000000000000000000000000000000000000000000 |!
1a
1h
#30000
0a
b10 e
b11001000 f
1w!
1s!
0h
1Y!
0Z!
0x!
0u!
#35000
b1100100000000000000000000000000110010000000000000000000000000000000000000000000000000000000000000000000000000000000000000000000000000000000000000000000000000000000000000000000000000000000000000000000000000000000000000000000000000000000000000000000000000000000000000000000000000000000000000000000000000000000000000000000000000000000000000000000000000000000000000000000000000000000000000000000000000000000000000000000000000000000000000000000000000000000000000000000000000000000000000000000000000000000000000000000000000000000000000000000000000000000000000000000000000000000000000000000000000000000000000000000000000000000000000000000000000000000000000000000000000000000000000000000000000000000000000000000000000000000000000000000000000000000000000000000000000000000000000000000000000000000000000000000000000000000000000000000000000000000000000000000000000000000000000000000000000000000000000000000000000000000000000000000000000000000000000000000000000000000000000000000 |!
1a
1h
#40000
1R!
1O!
1N!
1+!
1*!
1.!
0a
b1 c
b10 d
0g
1n
0h
14!
0{!
#45000
1a
1h
#50000
0a
b1010 e
b10010001101000101011001111000 f
1g
0s!
0h
1v!
1W!
1u!
1q!
1p!
1^!
1n!
1l!
1f!
1e!
1h!
1{!
1a!
#55000
b1100100000000000000000000000000110010000000000000000000000000000000000000000000000000000000000000000000000000000000000000000000000000000000000000000000000000000000000000000000000000000000000000000000000000000000000000000000000000000000000000000000000000000000000000010010001101000101011001111000000000000000000000000000000000000000000000000000000000000000000000000000000000000000000000000000000000000000000000000000000000000000000000000000000000000000000000000000000000000000000000000000000000000000000000000000000000000000000000000000000000000000000000000000000000000000000000000000000000000000000000000000000000000000000000000000000000000000000000000000000000000000000000000000000000000000000000000000000000000000000000000000000000000000000000000000000000000000000000000000000000000000000000000000000000000000000000000000000000000000000000000000000000000000000000000000000000000000000000000000000000000000000000000000000000000000000000000000000000000000000000000000 |!
1a
1h
#60000
1P!
0R!
0N!
1S!
0.!
1-!
1,!
0a
b1010 c
b1 d
0g
1'!
1&!
1$!
1"!
1z
1y
1r
1u
1|
0n
0h
1k
15!
04!
1m
0{!
#65000
1a
1h
#70000
0a
b0 e
b11111111111111111111111111111111 f
1g
1y!
1s!
1o!
0h
0Y!
1r!
0W!
1z!
1x!
1c!
1d!
1_!
1`!
1]!
1{!
1m!
1b!
1i!
1\!
1k!
1g!
1[!
1j!
#75000
1a
1h
#80000
0P!
0O!
0S!
0+!
0*!
0-!
0,!
0a
b0 c
b0 d
0g
0'!
0&!
0$!
0"!
0z
0y
0r
0u
0|
0h
0k
05!
0m
0{!
